[{"year":"2019","month":"1","pickup_community_area":"1","count":"105315"}
,{"year":"2019","month":"1","pickup_community_area":"2","count":"76895"}
,{"year":"2019","month":"1","pickup_community_area":"3","count":"188046"}
,{"year":"2019","month":"1","pickup_community_area":"4","count":"97321"}
,{"year":"2019","month":"1","pickup_community_area":"5","count":"111091"}
,{"year":"2019","month":"1","pickup_community_area":"6","count":"608279"}
,{"year":"2019","month":"1","pickup_community_area":"7","count":"498093"}
,{"year":"2019","month":"1","pickup_community_area":"8","count":"1412473"}
,{"year":"2019","month":"1","pickup_community_area":"9","count":"7786"}
,{"year":"2019","month":"1","pickup_community_area":"10","count":"24702"}
,{"year":"2019","month":"1","pickup_community_area":"11","count":"22719"}
,{"year":"2019","month":"1","pickup_community_area":"12","count":"10412"}
,{"year":"2019","month":"1","pickup_community_area":"13","count":"20945"}
,{"year":"2019","month":"1","pickup_community_area":"14","count":"58055"}
,{"year":"2019","month":"1","pickup_community_area":"15","count":"56682"}
,{"year":"2019","month":"1","pickup_community_area":"16","count":"88361"}
,{"year":"2019","month":"1","pickup_community_area":"17","count":"22904"}
,{"year":"2019","month":"1","pickup_community_area":"18","count":"9608"}
,{"year":"2019","month":"1","pickup_community_area":"19","count":"65024"}
,{"year":"2019","month":"1","pickup_community_area":"20","count":"23912"}
,{"year":"2019","month":"1","pickup_community_area":"21","count":"99977"}
,{"year":"2019","month":"1","pickup_community_area":"22","count":"338477"}
,{"year":"2019","month":"1","pickup_community_area":"23","count":"72542"}
,{"year":"2019","month":"1","pickup_community_area":"24","count":"562174"}
,{"year":"2019","month":"1","pickup_community_area":"25","count":"94002"}
,{"year":"2019","month":"1","pickup_community_area":"26","count":"21697"}
,{"year":"2019","month":"1","pickup_community_area":"27","count":"36033"}
,{"year":"2019","month":"1","pickup_community_area":"28","count":"773466"}
,{"year":"2019","month":"1","pickup_community_area":"29","count":"55505"}
,{"year":"2019","month":"1","pickup_community_area":"30","count":"54677"}
,{"year":"2019","month":"1","pickup_community_area":"31","count":"107384"}
,{"year":"2019","month":"1","pickup_community_area":"32","count":"753281"}
,{"year":"2019","month":"1","pickup_community_area":"33","count":"147615"}
,{"year":"2019","month":"1","pickup_community_area":"34","count":"37219"}
,{"year":"2019","month":"1","pickup_community_area":"35","count":"57103"}
,{"year":"2019","month":"1","pickup_community_area":"36","count":"11025"}
,{"year":"2019","month":"1","pickup_community_area":"37","count":"7863"}
,{"year":"2019","month":"1","pickup_community_area":"38","count":"49938"}
,{"year":"2019","month":"1","pickup_community_area":"39","count":"40822"}
,{"year":"2019","month":"1","pickup_community_area":"40","count":"24083"}
,{"year":"2019","month":"1","pickup_community_area":"41","count":"134243"}
,{"year":"2019","month":"1","pickup_community_area":"42","count":"47095"}
,{"year":"2019","month":"1","pickup_community_area":"43","count":"66041"}
,{"year":"2019","month":"1","pickup_community_area":"44","count":"51110"}
,{"year":"2019","month":"1","pickup_community_area":"45","count":"9622"}
,{"year":"2019","month":"1","pickup_community_area":"46","count":"21649"}
,{"year":"2019","month":"1","pickup_community_area":"47","count":"3255"}
,{"year":"2019","month":"1","pickup_community_area":"48","count":"10978"}
,{"year":"2019","month":"1","pickup_community_area":"49","count":"41151"}
,{"year":"2019","month":"1","pickup_community_area":"50","count":"9092"}
,{"year":"2019","month":"1","pickup_community_area":"51","count":"10946"}
,{"year":"2019","month":"1","pickup_community_area":"52","count":"3897"}
,{"year":"2019","month":"1","pickup_community_area":"53","count":"17570"}
,{"year":"2019","month":"1","pickup_community_area":"54","count":"5031"}
,{"year":"2019","month":"1","pickup_community_area":"55","count":"2823"}
,{"year":"2019","month":"1","pickup_community_area":"56","count":"90880"}
,{"year":"2019","month":"1","pickup_community_area":"57","count":"16529"}
,{"year":"2019","month":"1","pickup_community_area":"58","count":"37482"}
,{"year":"2019","month":"1","pickup_community_area":"59","count":"20980"}
,{"year":"2019","month":"1","pickup_community_area":"60","count":"51502"}
,{"year":"2019","month":"1","pickup_community_area":"61","count":"41035"}
,{"year":"2019","month":"1","pickup_community_area":"62","count":"12996"}
,{"year":"2019","month":"1","pickup_community_area":"63","count":"26272"}
,{"year":"2019","month":"1","pickup_community_area":"64","count":"11677"}
,{"year":"2019","month":"1","pickup_community_area":"65","count":"21944"}
,{"year":"2019","month":"1","pickup_community_area":"66","count":"39614"}
,{"year":"2019","month":"1","pickup_community_area":"67","count":"30576"}
,{"year":"2019","month":"1","pickup_community_area":"68","count":"35592"}
,{"year":"2019","month":"1","pickup_community_area":"69","count":"46606"}
,{"year":"2019","month":"1","pickup_community_area":"70","count":"22643"}
,{"year":"2019","month":"1","pickup_community_area":"71","count":"45066"}
,{"year":"2019","month":"1","pickup_community_area":"72","count":"11626"}
,{"year":"2019","month":"1","pickup_community_area":"73","count":"22435"}
,{"year":"2019","month":"1","pickup_community_area":"74","count":"6971"}
,{"year":"2019","month":"1","pickup_community_area":"75","count":"15490"}
,{"year":"2019","month":"1","pickup_community_area":"76","count":"274158"}
,{"year":"2019","month":"1","pickup_community_area":"77","count":"128382"}
,{"year":"2019","month":"1","count":"486518"}
,{"year":"2019","month":"2","pickup_community_area":"1","count":"103362"}
,{"year":"2019","month":"2","pickup_community_area":"2","count":"73235"}
,{"year":"2019","month":"2","pickup_community_area":"3","count":"183709"}
,{"year":"2019","month":"2","pickup_community_area":"4","count":"93767"}
,{"year":"2019","month":"2","pickup_community_area":"5","count":"108155"}
,{"year":"2019","month":"2","pickup_community_area":"6","count":"580391"}
,{"year":"2019","month":"2","pickup_community_area":"7","count":"479064"}
,{"year":"2019","month":"2","pickup_community_area":"8","count":"1413786"}
,{"year":"2019","month":"2","pickup_community_area":"9","count":"7536"}
,{"year":"2019","month":"2","pickup_community_area":"10","count":"24598"}
,{"year":"2019","month":"2","pickup_community_area":"11","count":"23090"}
,{"year":"2019","month":"2","pickup_community_area":"12","count":"10354"}
,{"year":"2019","month":"2","pickup_community_area":"13","count":"21403"}
,{"year":"2019","month":"2","pickup_community_area":"14","count":"56728"}
,{"year":"2019","month":"2","pickup_community_area":"15","count":"56026"}
,{"year":"2019","month":"2","pickup_community_area":"16","count":"85932"}
,{"year":"2019","month":"2","pickup_community_area":"17","count":"22960"}
,{"year":"2019","month":"2","pickup_community_area":"18","count":"9269"}
,{"year":"2019","month":"2","pickup_community_area":"19","count":"64113"}
,{"year":"2019","month":"2","pickup_community_area":"20","count":"23271"}
,{"year":"2019","month":"2","pickup_community_area":"21","count":"96485"}
,{"year":"2019","month":"2","pickup_community_area":"22","count":"332141"}
,{"year":"2019","month":"2","pickup_community_area":"23","count":"72201"}
,{"year":"2019","month":"2","pickup_community_area":"24","count":"551861"}
,{"year":"2019","month":"2","pickup_community_area":"25","count":"98724"}
,{"year":"2019","month":"2","pickup_community_area":"26","count":"22653"}
,{"year":"2019","month":"2","pickup_community_area":"27","count":"38322"}
,{"year":"2019","month":"2","pickup_community_area":"28","count":"801907"}
,{"year":"2019","month":"2","pickup_community_area":"29","count":"59386"}
,{"year":"2019","month":"2","pickup_community_area":"30","count":"54814"}
,{"year":"2019","month":"2","pickup_community_area":"31","count":"109315"}
,{"year":"2019","month":"2","pickup_community_area":"32","count":"770013"}
,{"year":"2019","month":"2","pickup_community_area":"33","count":"158832"}
,{"year":"2019","month":"2","pickup_community_area":"34","count":"39850"}
,{"year":"2019","month":"2","pickup_community_area":"35","count":"61291"}
,{"year":"2019","month":"2","pickup_community_area":"36","count":"11208"}
,{"year":"2019","month":"2","pickup_community_area":"37","count":"8374"}
,{"year":"2019","month":"2","pickup_community_area":"38","count":"51904"}
,{"year":"2019","month":"2","pickup_community_area":"39","count":"41802"}
,{"year":"2019","month":"2","pickup_community_area":"40","count":"26342"}
,{"year":"2019","month":"2","pickup_community_area":"41","count":"140944"}
,{"year":"2019","month":"2","pickup_community_area":"42","count":"51145"}
,{"year":"2019","month":"2","pickup_community_area":"43","count":"68213"}
,{"year":"2019","month":"2","pickup_community_area":"44","count":"53706"}
,{"year":"2019","month":"2","pickup_community_area":"45","count":"10225"}
,{"year":"2019","month":"2","pickup_community_area":"46","count":"22778"}
,{"year":"2019","month":"2","pickup_community_area":"47","count":"3400"}
,{"year":"2019","month":"2","pickup_community_area":"48","count":"11395"}
,{"year":"2019","month":"2","pickup_community_area":"49","count":"44444"}
,{"year":"2019","month":"2","pickup_community_area":"50","count":"10073"}
,{"year":"2019","month":"2","pickup_community_area":"51","count":"11751"}
,{"year":"2019","month":"2","pickup_community_area":"52","count":"3941"}
,{"year":"2019","month":"2","pickup_community_area":"53","count":"18898"}
,{"year":"2019","month":"2","pickup_community_area":"54","count":"5697"}
,{"year":"2019","month":"2","pickup_community_area":"55","count":"3034"}
,{"year":"2019","month":"2","pickup_community_area":"56","count":"89880"}
,{"year":"2019","month":"2","pickup_community_area":"57","count":"16905"}
,{"year":"2019","month":"2","pickup_community_area":"58","count":"37419"}
,{"year":"2019","month":"2","pickup_community_area":"59","count":"21153"}
,{"year":"2019","month":"2","pickup_community_area":"60","count":"51075"}
,{"year":"2019","month":"2","pickup_community_area":"61","count":"42125"}
,{"year":"2019","month":"2","pickup_community_area":"62","count":"12968"}
,{"year":"2019","month":"2","pickup_community_area":"63","count":"25737"}
,{"year":"2019","month":"2","pickup_community_area":"64","count":"11525"}
,{"year":"2019","month":"2","pickup_community_area":"65","count":"22559"}
,{"year":"2019","month":"2","pickup_community_area":"66","count":"40421"}
,{"year":"2019","month":"2","pickup_community_area":"67","count":"33368"}
,{"year":"2019","month":"2","pickup_community_area":"68","count":"39248"}
,{"year":"2019","month":"2","pickup_community_area":"69","count":"49197"}
,{"year":"2019","month":"2","pickup_community_area":"70","count":"23780"}
,{"year":"2019","month":"2","pickup_community_area":"71","count":"48380"}
,{"year":"2019","month":"2","pickup_community_area":"72","count":"11288"}
,{"year":"2019","month":"2","pickup_community_area":"73","count":"23154"}
,{"year":"2019","month":"2","pickup_community_area":"74","count":"6612"}
,{"year":"2019","month":"2","pickup_community_area":"75","count":"15662"}
,{"year":"2019","month":"2","pickup_community_area":"76","count":"273859"}
,{"year":"2019","month":"2","pickup_community_area":"77","count":"126140"}
,{"year":"2019","month":"2","count":"519042"}
,{"year":"2019","month":"3","pickup_community_area":"1","count":"113071"}
,{"year":"2019","month":"3","pickup_community_area":"2","count":"82373"}
,{"year":"2019","month":"3","pickup_community_area":"3","count":"208208"}
,{"year":"2019","month":"3","pickup_community_area":"4","count":"102974"}
,{"year":"2019","month":"3","pickup_community_area":"5","count":"123143"}
,{"year":"2019","month":"3","pickup_community_area":"6","count":"687936"}
,{"year":"2019","month":"3","pickup_community_area":"7","count":"555898"}
,{"year":"2019","month":"3","pickup_community_area":"8","count":"1671613"}
,{"year":"2019","month":"3","pickup_community_area":"9","count":"10119"}
,{"year":"2019","month":"3","pickup_community_area":"10","count":"29724"}
,{"year":"2019","month":"3","pickup_community_area":"11","count":"25872"}
,{"year":"2019","month":"3","pickup_community_area":"12","count":"12342"}
,{"year":"2019","month":"3","pickup_community_area":"13","count":"23343"}
,{"year":"2019","month":"3","pickup_community_area":"14","count":"62583"}
,{"year":"2019","month":"3","pickup_community_area":"15","count":"63624"}
,{"year":"2019","month":"3","pickup_community_area":"16","count":"98030"}
,{"year":"2019","month":"3","pickup_community_area":"17","count":"25937"}
,{"year":"2019","month":"3","pickup_community_area":"18","count":"10412"}
,{"year":"2019","month":"3","pickup_community_area":"19","count":"73325"}
,{"year":"2019","month":"3","pickup_community_area":"20","count":"26433"}
,{"year":"2019","month":"3","pickup_community_area":"21","count":"110499"}
,{"year":"2019","month":"3","pickup_community_area":"22","count":"376618"}
,{"year":"2019","month":"3","pickup_community_area":"23","count":"85892"}
,{"year":"2019","month":"3","pickup_community_area":"24","count":"635300"}
,{"year":"2019","month":"3","pickup_community_area":"25","count":"123531"}
,{"year":"2019","month":"3","pickup_community_area":"26","count":"29582"}
,{"year":"2019","month":"3","pickup_community_area":"27","count":"45949"}
,{"year":"2019","month":"3","pickup_community_area":"28","count":"891546"}
,{"year":"2019","month":"3","pickup_community_area":"29","count":"71910"}
,{"year":"2019","month":"3","pickup_community_area":"30","count":"62353"}
,{"year":"2019","month":"3","pickup_community_area":"31","count":"121921"}
,{"year":"2019","month":"3","pickup_community_area":"32","count":"880507"}
,{"year":"2019","month":"3","pickup_community_area":"33","count":"189098"}
,{"year":"2019","month":"3","pickup_community_area":"34","count":"47720"}
,{"year":"2019","month":"3","pickup_community_area":"35","count":"70262"}
,{"year":"2019","month":"3","pickup_community_area":"36","count":"13676"}
,{"year":"2019","month":"3","pickup_community_area":"37","count":"9838"}
,{"year":"2019","month":"3","pickup_community_area":"38","count":"60907"}
,{"year":"2019","month":"3","pickup_community_area":"39","count":"47057"}
,{"year":"2019","month":"3","pickup_community_area":"40","count":"31884"}
,{"year":"2019","month":"3","pickup_community_area":"41","count":"139879"}
,{"year":"2019","month":"3","pickup_community_area":"42","count":"59654"}
,{"year":"2019","month":"3","pickup_community_area":"43","count":"83760"}
,{"year":"2019","month":"3","pickup_community_area":"44","count":"65299"}
,{"year":"2019","month":"3","pickup_community_area":"45","count":"12109"}
,{"year":"2019","month":"3","pickup_community_area":"46","count":"27849"}
,{"year":"2019","month":"3","pickup_community_area":"47","count":"4038"}
,{"year":"2019","month":"3","pickup_community_area":"48","count":"13472"}
,{"year":"2019","month":"3","pickup_community_area":"49","count":"52680"}
,{"year":"2019","month":"3","pickup_community_area":"50","count":"12069"}
,{"year":"2019","month":"3","pickup_community_area":"51","count":"13415"}
,{"year":"2019","month":"3","pickup_community_area":"52","count":"4468"}
,{"year":"2019","month":"3","pickup_community_area":"53","count":"23428"}
,{"year":"2019","month":"3","pickup_community_area":"54","count":"7249"}
,{"year":"2019","month":"3","pickup_community_area":"55","count":"2897"}
,{"year":"2019","month":"3","pickup_community_area":"56","count":"115419"}
,{"year":"2019","month":"3","pickup_community_area":"57","count":"19266"}
,{"year":"2019","month":"3","pickup_community_area":"58","count":"42565"}
,{"year":"2019","month":"3","pickup_community_area":"59","count":"23372"}
,{"year":"2019","month":"3","pickup_community_area":"60","count":"57008"}
,{"year":"2019","month":"3","pickup_community_area":"61","count":"49426"}
,{"year":"2019","month":"3","pickup_community_area":"62","count":"14930"}
,{"year":"2019","month":"3","pickup_community_area":"63","count":"29267"}
,{"year":"2019","month":"3","pickup_community_area":"64","count":"13516"}
,{"year":"2019","month":"3","pickup_community_area":"65","count":"27083"}
,{"year":"2019","month":"3","pickup_community_area":"66","count":"49937"}
,{"year":"2019","month":"3","pickup_community_area":"67","count":"42359"}
,{"year":"2019","month":"3","pickup_community_area":"68","count":"48639"}
,{"year":"2019","month":"3","pickup_community_area":"69","count":"61429"}
,{"year":"2019","month":"3","pickup_community_area":"70","count":"27885"}
,{"year":"2019","month":"3","pickup_community_area":"71","count":"61219"}
,{"year":"2019","month":"3","pickup_community_area":"72","count":"15073"}
,{"year":"2019","month":"3","pickup_community_area":"73","count":"28223"}
,{"year":"2019","month":"3","pickup_community_area":"74","count":"8884"}
,{"year":"2019","month":"3","pickup_community_area":"75","count":"20191"}
,{"year":"2019","month":"3","pickup_community_area":"76","count":"324571"}
,{"year":"2019","month":"3","pickup_community_area":"77","count":"140230"}
,{"year":"2019","month":"3","count":"613375"}
,{"year":"2019","month":"4","pickup_community_area":"1","count":"101279"}
,{"year":"2019","month":"4","pickup_community_area":"2","count":"73891"}
,{"year":"2019","month":"4","pickup_community_area":"3","count":"183854"}
,{"year":"2019","month":"4","pickup_community_area":"4","count":"92163"}
,{"year":"2019","month":"4","pickup_community_area":"5","count":"105747"}
,{"year":"2019","month":"4","pickup_community_area":"6","count":"606770"}
,{"year":"2019","month":"4","pickup_community_area":"7","count":"475174"}
,{"year":"2019","month":"4","pickup_community_area":"8","count":"1495363"}
,{"year":"2019","month":"4","pickup_community_area":"9","count":"7570"}
,{"year":"2019","month":"4","pickup_community_area":"10","count":"25698"}
,{"year":"2019","month":"4","pickup_community_area":"11","count":"23378"}
,{"year":"2019","month":"4","pickup_community_area":"12","count":"11026"}
,{"year":"2019","month":"4","pickup_community_area":"13","count":"21841"}
,{"year":"2019","month":"4","pickup_community_area":"14","count":"55859"}
,{"year":"2019","month":"4","pickup_community_area":"15","count":"56072"}
,{"year":"2019","month":"4","pickup_community_area":"16","count":"86407"}
,{"year":"2019","month":"4","pickup_community_area":"17","count":"22754"}
,{"year":"2019","month":"4","pickup_community_area":"18","count":"9369"}
,{"year":"2019","month":"4","pickup_community_area":"19","count":"65791"}
,{"year":"2019","month":"4","pickup_community_area":"20","count":"24150"}
,{"year":"2019","month":"4","pickup_community_area":"21","count":"97306"}
,{"year":"2019","month":"4","pickup_community_area":"22","count":"326029"}
,{"year":"2019","month":"4","pickup_community_area":"23","count":"72718"}
,{"year":"2019","month":"4","pickup_community_area":"24","count":"551488"}
,{"year":"2019","month":"4","pickup_community_area":"25","count":"99566"}
,{"year":"2019","month":"4","pickup_community_area":"26","count":"22475"}
,{"year":"2019","month":"4","pickup_community_area":"27","count":"37761"}
,{"year":"2019","month":"4","pickup_community_area":"28","count":"793229"}
,{"year":"2019","month":"4","pickup_community_area":"29","count":"56656"}
,{"year":"2019","month":"4","pickup_community_area":"30","count":"55926"}
,{"year":"2019","month":"4","pickup_community_area":"31","count":"111421"}
,{"year":"2019","month":"4","pickup_community_area":"32","count":"834312"}
,{"year":"2019","month":"4","pickup_community_area":"33","count":"205028"}
,{"year":"2019","month":"4","pickup_community_area":"34","count":"46046"}
,{"year":"2019","month":"4","pickup_community_area":"35","count":"62647"}
,{"year":"2019","month":"4","pickup_community_area":"36","count":"11637"}
,{"year":"2019","month":"4","pickup_community_area":"37","count":"7965"}
,{"year":"2019","month":"4","pickup_community_area":"38","count":"52540"}
,{"year":"2019","month":"4","pickup_community_area":"39","count":"42162"}
,{"year":"2019","month":"4","pickup_community_area":"40","count":"26164"}
,{"year":"2019","month":"4","pickup_community_area":"41","count":"142468"}
,{"year":"2019","month":"4","pickup_community_area":"42","count":"52706"}
,{"year":"2019","month":"4","pickup_community_area":"43","count":"70006"}
,{"year":"2019","month":"4","pickup_community_area":"44","count":"52601"}
,{"year":"2019","month":"4","pickup_community_area":"45","count":"10180"}
,{"year":"2019","month":"4","pickup_community_area":"46","count":"22483"}
,{"year":"2019","month":"4","pickup_community_area":"47","count":"3382"}
,{"year":"2019","month":"4","pickup_community_area":"48","count":"11548"}
,{"year":"2019","month":"4","pickup_community_area":"49","count":"43241"}
,{"year":"2019","month":"4","pickup_community_area":"50","count":"9624"}
,{"year":"2019","month":"4","pickup_community_area":"51","count":"10878"}
,{"year":"2019","month":"4","pickup_community_area":"52","count":"4091"}
,{"year":"2019","month":"4","pickup_community_area":"53","count":"18437"}
,{"year":"2019","month":"4","pickup_community_area":"54","count":"5177"}
,{"year":"2019","month":"4","pickup_community_area":"55","count":"2517"}
,{"year":"2019","month":"4","pickup_community_area":"56","count":"118850"}
,{"year":"2019","month":"4","pickup_community_area":"57","count":"17565"}
,{"year":"2019","month":"4","pickup_community_area":"58","count":"38496"}
,{"year":"2019","month":"4","pickup_community_area":"59","count":"20929"}
,{"year":"2019","month":"4","pickup_community_area":"60","count":"52509"}
,{"year":"2019","month":"4","pickup_community_area":"61","count":"41983"}
,{"year":"2019","month":"4","pickup_community_area":"62","count":"13152"}
,{"year":"2019","month":"4","pickup_community_area":"63","count":"26382"}
,{"year":"2019","month":"4","pickup_community_area":"64","count":"12203"}
,{"year":"2019","month":"4","pickup_community_area":"65","count":"24585"}
,{"year":"2019","month":"4","pickup_community_area":"66","count":"41324"}
,{"year":"2019","month":"4","pickup_community_area":"67","count":"33693"}
,{"year":"2019","month":"4","pickup_community_area":"68","count":"39608"}
,{"year":"2019","month":"4","pickup_community_area":"69","count":"49533"}
,{"year":"2019","month":"4","pickup_community_area":"70","count":"24809"}
,{"year":"2019","month":"4","pickup_community_area":"71","count":"48479"}
,{"year":"2019","month":"4","pickup_community_area":"72","count":"11400"}
,{"year":"2019","month":"4","pickup_community_area":"73","count":"23359"}
,{"year":"2019","month":"4","pickup_community_area":"74","count":"6539"}
,{"year":"2019","month":"4","pickup_community_area":"75","count":"15874"}
,{"year":"2019","month":"4","pickup_community_area":"76","count":"338574"}
,{"year":"2019","month":"4","pickup_community_area":"77","count":"125486"}
,{"year":"2019","month":"4","count":"569908"}
,{"year":"2019","month":"5","pickup_community_area":"1","count":"102329"}
,{"year":"2019","month":"5","pickup_community_area":"2","count":"77114"}
,{"year":"2019","month":"5","pickup_community_area":"3","count":"196440"}
,{"year":"2019","month":"5","pickup_community_area":"4","count":"95837"}
,{"year":"2019","month":"5","pickup_community_area":"5","count":"113592"}
,{"year":"2019","month":"5","pickup_community_area":"6","count":"651461"}
,{"year":"2019","month":"5","pickup_community_area":"7","count":"510281"}
,{"year":"2019","month":"5","pickup_community_area":"8","count":"1589070"}
,{"year":"2019","month":"5","pickup_community_area":"9","count":"8217"}
,{"year":"2019","month":"5","pickup_community_area":"10","count":"28939"}
,{"year":"2019","month":"5","pickup_community_area":"11","count":"25071"}
,{"year":"2019","month":"5","pickup_community_area":"12","count":"12454"}
,{"year":"2019","month":"5","pickup_community_area":"13","count":"21072"}
,{"year":"2019","month":"5","pickup_community_area":"14","count":"56743"}
,{"year":"2019","month":"5","pickup_community_area":"15","count":"59063"}
,{"year":"2019","month":"5","pickup_community_area":"16","count":"91211"}
,{"year":"2019","month":"5","pickup_community_area":"17","count":"24294"}
,{"year":"2019","month":"5","pickup_community_area":"18","count":"9759"}
,{"year":"2019","month":"5","pickup_community_area":"19","count":"67913"}
,{"year":"2019","month":"5","pickup_community_area":"20","count":"24399"}
,{"year":"2019","month":"5","pickup_community_area":"21","count":"100334"}
,{"year":"2019","month":"5","pickup_community_area":"22","count":"340523"}
,{"year":"2019","month":"5","pickup_community_area":"23","count":"74901"}
,{"year":"2019","month":"5","pickup_community_area":"24","count":"579799"}
,{"year":"2019","month":"5","pickup_community_area":"25","count":"98900"}
,{"year":"2019","month":"5","pickup_community_area":"26","count":"22149"}
,{"year":"2019","month":"5","pickup_community_area":"27","count":"40046"}
,{"year":"2019","month":"5","pickup_community_area":"28","count":"807601"}
,{"year":"2019","month":"5","pickup_community_area":"29","count":"56362"}
,{"year":"2019","month":"5","pickup_community_area":"30","count":"58862"}
,{"year":"2019","month":"5","pickup_community_area":"31","count":"120288"}
,{"year":"2019","month":"5","pickup_community_area":"32","count":"889821"}
,{"year":"2019","month":"5","pickup_community_area":"33","count":"226973"}
,{"year":"2019","month":"5","pickup_community_area":"34","count":"55085"}
,{"year":"2019","month":"5","pickup_community_area":"35","count":"63635"}
,{"year":"2019","month":"5","pickup_community_area":"36","count":"12142"}
,{"year":"2019","month":"5","pickup_community_area":"37","count":"7602"}
,{"year":"2019","month":"5","pickup_community_area":"38","count":"53406"}
,{"year":"2019","month":"5","pickup_community_area":"39","count":"44034"}
,{"year":"2019","month":"5","pickup_community_area":"40","count":"25204"}
,{"year":"2019","month":"5","pickup_community_area":"41","count":"140504"}
,{"year":"2019","month":"5","pickup_community_area":"42","count":"52244"}
,{"year":"2019","month":"5","pickup_community_area":"43","count":"69313"}
,{"year":"2019","month":"5","pickup_community_area":"44","count":"53472"}
,{"year":"2019","month":"5","pickup_community_area":"45","count":"10754"}
,{"year":"2019","month":"5","pickup_community_area":"46","count":"22869"}
,{"year":"2019","month":"5","pickup_community_area":"47","count":"3421"}
,{"year":"2019","month":"5","pickup_community_area":"48","count":"11654"}
,{"year":"2019","month":"5","pickup_community_area":"49","count":"43289"}
,{"year":"2019","month":"5","pickup_community_area":"50","count":"9827"}
,{"year":"2019","month":"5","pickup_community_area":"51","count":"11611"}
,{"year":"2019","month":"5","pickup_community_area":"52","count":"4496"}
,{"year":"2019","month":"5","pickup_community_area":"53","count":"18549"}
,{"year":"2019","month":"5","pickup_community_area":"54","count":"5342"}
,{"year":"2019","month":"5","pickup_community_area":"55","count":"2704"}
,{"year":"2019","month":"5","pickup_community_area":"56","count":"128490"}
,{"year":"2019","month":"5","pickup_community_area":"57","count":"18389"}
,{"year":"2019","month":"5","pickup_community_area":"58","count":"39329"}
,{"year":"2019","month":"5","pickup_community_area":"59","count":"21815"}
,{"year":"2019","month":"5","pickup_community_area":"60","count":"54506"}
,{"year":"2019","month":"5","pickup_community_area":"61","count":"42529"}
,{"year":"2019","month":"5","pickup_community_area":"62","count":"13761"}
,{"year":"2019","month":"5","pickup_community_area":"63","count":"27125"}
,{"year":"2019","month":"5","pickup_community_area":"64","count":"12902"}
,{"year":"2019","month":"5","pickup_community_area":"65","count":"25359"}
,{"year":"2019","month":"5","pickup_community_area":"66","count":"42674"}
,{"year":"2019","month":"5","pickup_community_area":"67","count":"32809"}
,{"year":"2019","month":"5","pickup_community_area":"68","count":"37968"}
,{"year":"2019","month":"5","pickup_community_area":"69","count":"48987"}
,{"year":"2019","month":"5","pickup_community_area":"70","count":"25615"}
,{"year":"2019","month":"5","pickup_community_area":"71","count":"48490"}
,{"year":"2019","month":"5","pickup_community_area":"72","count":"13115"}
,{"year":"2019","month":"5","pickup_community_area":"73","count":"24499"}
,{"year":"2019","month":"5","pickup_community_area":"74","count":"7374"}
,{"year":"2019","month":"5","pickup_community_area":"75","count":"16541"}
,{"year":"2019","month":"5","pickup_community_area":"76","count":"373657"}
,{"year":"2019","month":"5","pickup_community_area":"77","count":"128848"}
,{"year":"2019","month":"5","count":"619134"}
,{"year":"2019","month":"6","pickup_community_area":"1","count":"93992"}
,{"year":"2019","month":"6","pickup_community_area":"2","count":"73191"}
,{"year":"2019","month":"6","pickup_community_area":"3","count":"193689"}
,{"year":"2019","month":"6","pickup_community_area":"4","count":"95184"}
,{"year":"2019","month":"6","pickup_community_area":"5","count":"116241"}
,{"year":"2019","month":"6","pickup_community_area":"6","count":"663720"}
,{"year":"2019","month":"6","pickup_community_area":"7","count":"522556"}
,{"year":"2019","month":"6","pickup_community_area":"8","count":"1580270"}
,{"year":"2019","month":"6","pickup_community_area":"9","count":"8834"}
,{"year":"2019","month":"6","pickup_community_area":"10","count":"28997"}
,{"year":"2019","month":"6","pickup_community_area":"11","count":"25119"}
,{"year":"2019","month":"6","pickup_community_area":"12","count":"12866"}
,{"year":"2019","month":"6","pickup_community_area":"13","count":"19268"}
,{"year":"2019","month":"6","pickup_community_area":"14","count":"54490"}
,{"year":"2019","month":"6","pickup_community_area":"15","count":"56997"}
,{"year":"2019","month":"6","pickup_community_area":"16","count":"88385"}
,{"year":"2019","month":"6","pickup_community_area":"17","count":"23560"}
,{"year":"2019","month":"6","pickup_community_area":"18","count":"9166"}
,{"year":"2019","month":"6","pickup_community_area":"19","count":"63957"}
,{"year":"2019","month":"6","pickup_community_area":"20","count":"23244"}
,{"year":"2019","month":"6","pickup_community_area":"21","count":"97218"}
,{"year":"2019","month":"6","pickup_community_area":"22","count":"335967"}
,{"year":"2019","month":"6","pickup_community_area":"23","count":"69411"}
,{"year":"2019","month":"6","pickup_community_area":"24","count":"579834"}
,{"year":"2019","month":"6","pickup_community_area":"25","count":"91892"}
,{"year":"2019","month":"6","pickup_community_area":"26","count":"19912"}
,{"year":"2019","month":"6","pickup_community_area":"27","count":"35024"}
,{"year":"2019","month":"6","pickup_community_area":"28","count":"799898"}
,{"year":"2019","month":"6","pickup_community_area":"29","count":"57457"}
,{"year":"2019","month":"6","pickup_community_area":"30","count":"56091"}
,{"year":"2019","month":"6","pickup_community_area":"31","count":"110579"}
,{"year":"2019","month":"6","pickup_community_area":"32","count":"876978"}
,{"year":"2019","month":"6","pickup_community_area":"33","count":"233225"}
,{"year":"2019","month":"6","pickup_community_area":"34","count":"49780"}
,{"year":"2019","month":"6","pickup_community_area":"35","count":"57859"}
,{"year":"2019","month":"6","pickup_community_area":"36","count":"11801"}
,{"year":"2019","month":"6","pickup_community_area":"37","count":"7342"}
,{"year":"2019","month":"6","pickup_community_area":"38","count":"50185"}
,{"year":"2019","month":"6","pickup_community_area":"39","count":"43385"}
,{"year":"2019","month":"6","pickup_community_area":"40","count":"22929"}
,{"year":"2019","month":"6","pickup_community_area":"41","count":"129241"}
,{"year":"2019","month":"6","pickup_community_area":"42","count":"46567"}
,{"year":"2019","month":"6","pickup_community_area":"43","count":"64309"}
,{"year":"2019","month":"6","pickup_community_area":"44","count":"48422"}
,{"year":"2019","month":"6","pickup_community_area":"45","count":"10178"}
,{"year":"2019","month":"6","pickup_community_area":"46","count":"20567"}
,{"year":"2019","month":"6","pickup_community_area":"47","count":"3254"}
,{"year":"2019","month":"6","pickup_community_area":"48","count":"10502"}
,{"year":"2019","month":"6","pickup_community_area":"49","count":"38843"}
,{"year":"2019","month":"6","pickup_community_area":"50","count":"8686"}
,{"year":"2019","month":"6","pickup_community_area":"51","count":"10734"}
,{"year":"2019","month":"6","pickup_community_area":"52","count":"4072"}
,{"year":"2019","month":"6","pickup_community_area":"53","count":"16924"}
,{"year":"2019","month":"6","pickup_community_area":"54","count":"4698"}
,{"year":"2019","month":"6","pickup_community_area":"55","count":"2709"}
,{"year":"2019","month":"6","pickup_community_area":"56","count":"117532"}
,{"year":"2019","month":"6","pickup_community_area":"57","count":"17983"}
,{"year":"2019","month":"6","pickup_community_area":"58","count":"37013"}
,{"year":"2019","month":"6","pickup_community_area":"59","count":"20595"}
,{"year":"2019","month":"6","pickup_community_area":"60","count":"51302"}
,{"year":"2019","month":"6","pickup_community_area":"61","count":"39683"}
,{"year":"2019","month":"6","pickup_community_area":"62","count":"13375"}
,{"year":"2019","month":"6","pickup_community_area":"63","count":"25347"}
,{"year":"2019","month":"6","pickup_community_area":"64","count":"12639"}
,{"year":"2019","month":"6","pickup_community_area":"65","count":"24519"}
,{"year":"2019","month":"6","pickup_community_area":"66","count":"39930"}
,{"year":"2019","month":"6","pickup_community_area":"67","count":"28637"}
,{"year":"2019","month":"6","pickup_community_area":"68","count":"33375"}
,{"year":"2019","month":"6","pickup_community_area":"69","count":"44698"}
,{"year":"2019","month":"6","pickup_community_area":"70","count":"23696"}
,{"year":"2019","month":"6","pickup_community_area":"71","count":"44049"}
,{"year":"2019","month":"6","pickup_community_area":"72","count":"13568"}
,{"year":"2019","month":"6","pickup_community_area":"73","count":"22328"}
,{"year":"2019","month":"6","pickup_community_area":"74","count":"6915"}
,{"year":"2019","month":"6","pickup_community_area":"75","count":"15365"}
,{"year":"2019","month":"6","pickup_community_area":"76","count":"363875"}
,{"year":"2019","month":"6","pickup_community_area":"77","count":"126259"}
,{"year":"2019","month":"6","count":"615911"}
,{"year":"2019","month":"7","pickup_community_area":"1","count":"90130"}
,{"year":"2019","month":"7","pickup_community_area":"2","count":"70271"}
,{"year":"2019","month":"7","pickup_community_area":"3","count":"187700"}
,{"year":"2019","month":"7","pickup_community_area":"4","count":"88337"}
,{"year":"2019","month":"7","pickup_community_area":"5","count":"108517"}
,{"year":"2019","month":"7","pickup_community_area":"6","count":"592255"}
,{"year":"2019","month":"7","pickup_community_area":"7","count":"497559"}
,{"year":"2019","month":"7","pickup_community_area":"8","count":"1528084"}
,{"year":"2019","month":"7","pickup_community_area":"9","count":"7933"}
,{"year":"2019","month":"7","pickup_community_area":"10","count":"27332"}
,{"year":"2019","month":"7","pickup_community_area":"11","count":"25992"}
,{"year":"2019","month":"7","pickup_community_area":"12","count":"12107"}
,{"year":"2019","month":"7","pickup_community_area":"13","count":"18007"}
,{"year":"2019","month":"7","pickup_community_area":"14","count":"52259"}
,{"year":"2019","month":"7","pickup_community_area":"15","count":"55370"}
,{"year":"2019","month":"7","pickup_community_area":"16","count":"86251"}
,{"year":"2019","month":"7","pickup_community_area":"17","count":"23163"}
,{"year":"2019","month":"7","pickup_community_area":"18","count":"9269"}
,{"year":"2019","month":"7","pickup_community_area":"19","count":"62185"}
,{"year":"2019","month":"7","pickup_community_area":"20","count":"23290"}
,{"year":"2019","month":"7","pickup_community_area":"21","count":"94986"}
,{"year":"2019","month":"7","pickup_community_area":"22","count":"322688"}
,{"year":"2019","month":"7","pickup_community_area":"23","count":"68123"}
,{"year":"2019","month":"7","pickup_community_area":"24","count":"570072"}
,{"year":"2019","month":"7","pickup_community_area":"25","count":"91114"}
,{"year":"2019","month":"7","pickup_community_area":"26","count":"19874"}
,{"year":"2019","month":"7","pickup_community_area":"27","count":"34455"}
,{"year":"2019","month":"7","pickup_community_area":"28","count":"784502"}
,{"year":"2019","month":"7","pickup_community_area":"29","count":"51589"}
,{"year":"2019","month":"7","pickup_community_area":"30","count":"53961"}
,{"year":"2019","month":"7","pickup_community_area":"31","count":"110667"}
,{"year":"2019","month":"7","pickup_community_area":"32","count":"854688"}
,{"year":"2019","month":"7","pickup_community_area":"33","count":"195660"}
,{"year":"2019","month":"7","pickup_community_area":"34","count":"49265"}
,{"year":"2019","month":"7","pickup_community_area":"35","count":"59721"}
,{"year":"2019","month":"7","pickup_community_area":"36","count":"12018"}
,{"year":"2019","month":"7","pickup_community_area":"37","count":"6830"}
,{"year":"2019","month":"7","pickup_community_area":"38","count":"50111"}
,{"year":"2019","month":"7","pickup_community_area":"39","count":"40939"}
,{"year":"2019","month":"7","pickup_community_area":"40","count":"22860"}
,{"year":"2019","month":"7","pickup_community_area":"41","count":"107053"}
,{"year":"2019","month":"7","pickup_community_area":"42","count":"43902"}
,{"year":"2019","month":"7","pickup_community_area":"43","count":"63505"}
,{"year":"2019","month":"7","pickup_community_area":"44","count":"49069"}
,{"year":"2019","month":"7","pickup_community_area":"45","count":"10165"}
,{"year":"2019","month":"7","pickup_community_area":"46","count":"20953"}
,{"year":"2019","month":"7","pickup_community_area":"47","count":"3212"}
,{"year":"2019","month":"7","pickup_community_area":"48","count":"10829"}
,{"year":"2019","month":"7","pickup_community_area":"49","count":"39217"}
,{"year":"2019","month":"7","pickup_community_area":"50","count":"8625"}
,{"year":"2019","month":"7","pickup_community_area":"51","count":"11084"}
,{"year":"2019","month":"7","pickup_community_area":"52","count":"4129"}
,{"year":"2019","month":"7","pickup_community_area":"53","count":"17236"}
,{"year":"2019","month":"7","pickup_community_area":"54","count":"4806"}
,{"year":"2019","month":"7","pickup_community_area":"55","count":"2767"}
,{"year":"2019","month":"7","pickup_community_area":"56","count":"112291"}
,{"year":"2019","month":"7","pickup_community_area":"57","count":"16795"}
,{"year":"2019","month":"7","pickup_community_area":"58","count":"35996"}
,{"year":"2019","month":"7","pickup_community_area":"59","count":"19783"}
,{"year":"2019","month":"7","pickup_community_area":"60","count":"49955"}
,{"year":"2019","month":"7","pickup_community_area":"61","count":"38326"}
,{"year":"2019","month":"7","pickup_community_area":"62","count":"12988"}
,{"year":"2019","month":"7","pickup_community_area":"63","count":"24566"}
,{"year":"2019","month":"7","pickup_community_area":"64","count":"13072"}
,{"year":"2019","month":"7","pickup_community_area":"65","count":"23064"}
,{"year":"2019","month":"7","pickup_community_area":"66","count":"38689"}
,{"year":"2019","month":"7","pickup_community_area":"67","count":"27650"}
,{"year":"2019","month":"7","pickup_community_area":"68","count":"33020"}
,{"year":"2019","month":"7","pickup_community_area":"69","count":"43961"}
,{"year":"2019","month":"7","pickup_community_area":"70","count":"23678"}
,{"year":"2019","month":"7","pickup_community_area":"71","count":"43128"}
,{"year":"2019","month":"7","pickup_community_area":"72","count":"13250"}
,{"year":"2019","month":"7","pickup_community_area":"73","count":"22248"}
,{"year":"2019","month":"7","pickup_community_area":"74","count":"6497"}
,{"year":"2019","month":"7","pickup_community_area":"75","count":"15055"}
,{"year":"2019","month":"7","pickup_community_area":"76","count":"360420"}
,{"year":"2019","month":"7","pickup_community_area":"77","count":"121713"}
,{"year":"2019","month":"7","count":"585989"}
,{"year":"2019","month":"8","pickup_community_area":"1","count":"94285"}
,{"year":"2019","month":"8","pickup_community_area":"2","count":"70029"}
,{"year":"2019","month":"8","pickup_community_area":"3","count":"196004"}
,{"year":"2019","month":"8","pickup_community_area":"4","count":"90782"}
,{"year":"2019","month":"8","pickup_community_area":"5","count":"112966"}
,{"year":"2019","month":"8","pickup_community_area":"6","count":"645598"}
,{"year":"2019","month":"8","pickup_community_area":"7","count":"515192"}
,{"year":"2019","month":"8","pickup_community_area":"8","count":"1584127"}
,{"year":"2019","month":"8","pickup_community_area":"9","count":"9145"}
,{"year":"2019","month":"8","pickup_community_area":"10","count":"30196"}
,{"year":"2019","month":"8","pickup_community_area":"11","count":"26324"}
,{"year":"2019","month":"8","pickup_community_area":"12","count":"12619"}
,{"year":"2019","month":"8","pickup_community_area":"13","count":"18237"}
,{"year":"2019","month":"8","pickup_community_area":"14","count":"53820"}
,{"year":"2019","month":"8","pickup_community_area":"15","count":"56387"}
,{"year":"2019","month":"8","pickup_community_area":"16","count":"86628"}
,{"year":"2019","month":"8","pickup_community_area":"17","count":"24458"}
,{"year":"2019","month":"8","pickup_community_area":"18","count":"9505"}
,{"year":"2019","month":"8","pickup_community_area":"19","count":"65092"}
,{"year":"2019","month":"8","pickup_community_area":"20","count":"22945"}
,{"year":"2019","month":"8","pickup_community_area":"21","count":"99029"}
,{"year":"2019","month":"8","pickup_community_area":"22","count":"336182"}
,{"year":"2019","month":"8","pickup_community_area":"23","count":"69372"}
,{"year":"2019","month":"8","pickup_community_area":"24","count":"577063"}
,{"year":"2019","month":"8","pickup_community_area":"25","count":"91112"}
,{"year":"2019","month":"8","pickup_community_area":"26","count":"20253"}
,{"year":"2019","month":"8","pickup_community_area":"27","count":"34730"}
,{"year":"2019","month":"8","pickup_community_area":"28","count":"797459"}
,{"year":"2019","month":"8","pickup_community_area":"29","count":"52966"}
,{"year":"2019","month":"8","pickup_community_area":"30","count":"55186"}
,{"year":"2019","month":"8","pickup_community_area":"31","count":"109284"}
,{"year":"2019","month":"8","pickup_community_area":"32","count":"868391"}
,{"year":"2019","month":"8","pickup_community_area":"33","count":"201057"}
,{"year":"2019","month":"8","pickup_community_area":"34","count":"50042"}
,{"year":"2019","month":"8","pickup_community_area":"35","count":"59943"}
,{"year":"2019","month":"8","pickup_community_area":"36","count":"11389"}
,{"year":"2019","month":"8","pickup_community_area":"37","count":"6951"}
,{"year":"2019","month":"8","pickup_community_area":"38","count":"48071"}
,{"year":"2019","month":"8","pickup_community_area":"39","count":"38250"}
,{"year":"2019","month":"8","pickup_community_area":"40","count":"21575"}
,{"year":"2019","month":"8","pickup_community_area":"41","count":"100265"}
,{"year":"2019","month":"8","pickup_community_area":"42","count":"41963"}
,{"year":"2019","month":"8","pickup_community_area":"43","count":"62968"}
,{"year":"2019","month":"8","pickup_community_area":"44","count":"48717"}
,{"year":"2019","month":"8","pickup_community_area":"45","count":"9935"}
,{"year":"2019","month":"8","pickup_community_area":"46","count":"21319"}
,{"year":"2019","month":"8","pickup_community_area":"47","count":"3170"}
,{"year":"2019","month":"8","pickup_community_area":"48","count":"10763"}
,{"year":"2019","month":"8","pickup_community_area":"49","count":"39362"}
,{"year":"2019","month":"8","pickup_community_area":"50","count":"8857"}
,{"year":"2019","month":"8","pickup_community_area":"51","count":"11636"}
,{"year":"2019","month":"8","pickup_community_area":"52","count":"4278"}
,{"year":"2019","month":"8","pickup_community_area":"53","count":"17484"}
,{"year":"2019","month":"8","pickup_community_area":"54","count":"4950"}
,{"year":"2019","month":"8","pickup_community_area":"55","count":"3116"}
,{"year":"2019","month":"8","pickup_community_area":"56","count":"123794"}
,{"year":"2019","month":"8","pickup_community_area":"57","count":"17182"}
,{"year":"2019","month":"8","pickup_community_area":"58","count":"35899"}
,{"year":"2019","month":"8","pickup_community_area":"59","count":"20246"}
,{"year":"2019","month":"8","pickup_community_area":"60","count":"50714"}
,{"year":"2019","month":"8","pickup_community_area":"61","count":"39033"}
,{"year":"2019","month":"8","pickup_community_area":"62","count":"12931"}
,{"year":"2019","month":"8","pickup_community_area":"63","count":"25219"}
,{"year":"2019","month":"8","pickup_community_area":"64","count":"13694"}
,{"year":"2019","month":"8","pickup_community_area":"65","count":"24062"}
,{"year":"2019","month":"8","pickup_community_area":"66","count":"39391"}
,{"year":"2019","month":"8","pickup_community_area":"67","count":"28302"}
,{"year":"2019","month":"8","pickup_community_area":"68","count":"33487"}
,{"year":"2019","month":"8","pickup_community_area":"69","count":"45059"}
,{"year":"2019","month":"8","pickup_community_area":"70","count":"24525"}
,{"year":"2019","month":"8","pickup_community_area":"71","count":"43757"}
,{"year":"2019","month":"8","pickup_community_area":"72","count":"12797"}
,{"year":"2019","month":"8","pickup_community_area":"73","count":"21745"}
,{"year":"2019","month":"8","pickup_community_area":"74","count":"7102"}
,{"year":"2019","month":"8","pickup_community_area":"75","count":"14402"}
,{"year":"2019","month":"8","pickup_community_area":"76","count":"375857"}
,{"year":"2019","month":"8","pickup_community_area":"77","count":"126103"}
,{"year":"2019","month":"8","count":"610411"}
,{"year":"2019","month":"9","pickup_community_area":"1","count":"92605"}
,{"year":"2019","month":"9","pickup_community_area":"2","count":"66792"}
,{"year":"2019","month":"9","pickup_community_area":"3","count":"182745"}
,{"year":"2019","month":"9","pickup_community_area":"4","count":"87390"}
,{"year":"2019","month":"9","pickup_community_area":"5","count":"104352"}
,{"year":"2019","month":"9","pickup_community_area":"6","count":"586958"}
,{"year":"2019","month":"9","pickup_community_area":"7","count":"477925"}
,{"year":"2019","month":"9","pickup_community_area":"8","count":"1457263"}
,{"year":"2019","month":"9","pickup_community_area":"9","count":"7610"}
,{"year":"2019","month":"9","pickup_community_area":"10","count":"26395"}
,{"year":"2019","month":"9","pickup_community_area":"11","count":"22608"}
,{"year":"2019","month":"9","pickup_community_area":"12","count":"11126"}
,{"year":"2019","month":"9","pickup_community_area":"13","count":"19595"}
,{"year":"2019","month":"9","pickup_community_area":"14","count":"51803"}
,{"year":"2019","month":"9","pickup_community_area":"15","count":"53518"}
,{"year":"2019","month":"9","pickup_community_area":"16","count":"82566"}
,{"year":"2019","month":"9","pickup_community_area":"17","count":"23545"}
,{"year":"2019","month":"9","pickup_community_area":"18","count":"8621"}
,{"year":"2019","month":"9","pickup_community_area":"19","count":"61893"}
,{"year":"2019","month":"9","pickup_community_area":"20","count":"21641"}
,{"year":"2019","month":"9","pickup_community_area":"21","count":"94975"}
,{"year":"2019","month":"9","pickup_community_area":"22","count":"317770"}
,{"year":"2019","month":"9","pickup_community_area":"23","count":"66487"}
,{"year":"2019","month":"9","pickup_community_area":"24","count":"547119"}
,{"year":"2019","month":"9","pickup_community_area":"25","count":"85630"}
,{"year":"2019","month":"9","pickup_community_area":"26","count":"19211"}
,{"year":"2019","month":"9","pickup_community_area":"27","count":"33108"}
,{"year":"2019","month":"9","pickup_community_area":"28","count":"757073"}
,{"year":"2019","month":"9","pickup_community_area":"29","count":"62308"}
,{"year":"2019","month":"9","pickup_community_area":"30","count":"54912"}
,{"year":"2019","month":"9","pickup_community_area":"31","count":"103222"}
,{"year":"2019","month":"9","pickup_community_area":"32","count":"818855"}
,{"year":"2019","month":"9","pickup_community_area":"33","count":"200067"}
,{"year":"2019","month":"9","pickup_community_area":"34","count":"46254"}
,{"year":"2019","month":"9","pickup_community_area":"35","count":"54463"}
,{"year":"2019","month":"9","pickup_community_area":"36","count":"10093"}
,{"year":"2019","month":"9","pickup_community_area":"37","count":"6640"}
,{"year":"2019","month":"9","pickup_community_area":"38","count":"45203"}
,{"year":"2019","month":"9","pickup_community_area":"39","count":"36282"}
,{"year":"2019","month":"9","pickup_community_area":"40","count":"20919"}
,{"year":"2019","month":"9","pickup_community_area":"41","count":"102597"}
,{"year":"2019","month":"9","pickup_community_area":"42","count":"41196"}
,{"year":"2019","month":"9","pickup_community_area":"43","count":"60923"}
,{"year":"2019","month":"9","pickup_community_area":"44","count":"47084"}
,{"year":"2019","month":"9","pickup_community_area":"45","count":"9409"}
,{"year":"2019","month":"9","pickup_community_area":"46","count":"20206"}
,{"year":"2019","month":"9","pickup_community_area":"47","count":"3025"}
,{"year":"2019","month":"9","pickup_community_area":"48","count":"9670"}
,{"year":"2019","month":"9","pickup_community_area":"49","count":"38866"}
,{"year":"2019","month":"9","pickup_community_area":"50","count":"8725"}
,{"year":"2019","month":"9","pickup_community_area":"51","count":"10798"}
,{"year":"2019","month":"9","pickup_community_area":"52","count":"4218"}
,{"year":"2019","month":"9","pickup_community_area":"53","count":"16909"}
,{"year":"2019","month":"9","pickup_community_area":"54","count":"4764"}
,{"year":"2019","month":"9","pickup_community_area":"55","count":"3335"}
,{"year":"2019","month":"9","pickup_community_area":"56","count":"127030"}
,{"year":"2019","month":"9","pickup_community_area":"57","count":"16499"}
,{"year":"2019","month":"9","pickup_community_area":"58","count":"34443"}
,{"year":"2019","month":"9","pickup_community_area":"59","count":"19089"}
,{"year":"2019","month":"9","pickup_community_area":"60","count":"47877"}
,{"year":"2019","month":"9","pickup_community_area":"61","count":"37547"}
,{"year":"2019","month":"9","pickup_community_area":"62","count":"13009"}
,{"year":"2019","month":"9","pickup_community_area":"63","count":"23585"}
,{"year":"2019","month":"9","pickup_community_area":"64","count":"12630"}
,{"year":"2019","month":"9","pickup_community_area":"65","count":"22569"}
,{"year":"2019","month":"9","pickup_community_area":"66","count":"38731"}
,{"year":"2019","month":"9","pickup_community_area":"67","count":"27427"}
,{"year":"2019","month":"9","pickup_community_area":"68","count":"32204"}
,{"year":"2019","month":"9","pickup_community_area":"69","count":"42724"}
,{"year":"2019","month":"9","pickup_community_area":"70","count":"22665"}
,{"year":"2019","month":"9","pickup_community_area":"71","count":"41548"}
,{"year":"2019","month":"9","pickup_community_area":"72","count":"11600"}
,{"year":"2019","month":"9","pickup_community_area":"73","count":"20406"}
,{"year":"2019","month":"9","pickup_community_area":"74","count":"6693"}
,{"year":"2019","month":"9","pickup_community_area":"75","count":"14268"}
,{"year":"2019","month":"9","pickup_community_area":"76","count":"383700"}
,{"year":"2019","month":"9","pickup_community_area":"77","count":"116608"}
,{"year":"2019","month":"9","count":"594283"}
,{"year":"2019","month":"10","pickup_community_area":"1","count":"99808"}
,{"year":"2019","month":"10","pickup_community_area":"2","count":"70576"}
,{"year":"2019","month":"10","pickup_community_area":"3","count":"187093"}
,{"year":"2019","month":"10","pickup_community_area":"4","count":"93757"}
,{"year":"2019","month":"10","pickup_community_area":"5","count":"109495"}
,{"year":"2019","month":"10","pickup_community_area":"6","count":"574565"}
,{"year":"2019","month":"10","pickup_community_area":"7","count":"500647"}
,{"year":"2019","month":"10","pickup_community_area":"8","count":"1588762"}
,{"year":"2019","month":"10","pickup_community_area":"9","count":"7625"}
,{"year":"2019","month":"10","pickup_community_area":"10","count":"27341"}
,{"year":"2019","month":"10","pickup_community_area":"11","count":"23696"}
,{"year":"2019","month":"10","pickup_community_area":"12","count":"11780"}
,{"year":"2019","month":"10","pickup_community_area":"13","count":"20723"}
,{"year":"2019","month":"10","pickup_community_area":"14","count":"55045"}
,{"year":"2019","month":"10","pickup_community_area":"15","count":"57113"}
,{"year":"2019","month":"10","pickup_community_area":"16","count":"84423"}
,{"year":"2019","month":"10","pickup_community_area":"17","count":"24536"}
,{"year":"2019","month":"10","pickup_community_area":"18","count":"9250"}
,{"year":"2019","month":"10","pickup_community_area":"19","count":"63825"}
,{"year":"2019","month":"10","pickup_community_area":"20","count":"23296"}
,{"year":"2019","month":"10","pickup_community_area":"21","count":"97763"}
,{"year":"2019","month":"10","pickup_community_area":"22","count":"328180"}
,{"year":"2019","month":"10","pickup_community_area":"23","count":"68432"}
,{"year":"2019","month":"10","pickup_community_area":"24","count":"576771"}
,{"year":"2019","month":"10","pickup_community_area":"25","count":"90537"}
,{"year":"2019","month":"10","pickup_community_area":"26","count":"20052"}
,{"year":"2019","month":"10","pickup_community_area":"27","count":"33603"}
,{"year":"2019","month":"10","pickup_community_area":"28","count":"844698"}
,{"year":"2019","month":"10","pickup_community_area":"29","count":"51756"}
,{"year":"2019","month":"10","pickup_community_area":"30","count":"55099"}
,{"year":"2019","month":"10","pickup_community_area":"31","count":"111387"}
,{"year":"2019","month":"10","pickup_community_area":"32","count":"894272"}
,{"year":"2019","month":"10","pickup_community_area":"33","count":"216550"}
,{"year":"2019","month":"10","pickup_community_area":"34","count":"43035"}
,{"year":"2019","month":"10","pickup_community_area":"35","count":"55664"}
,{"year":"2019","month":"10","pickup_community_area":"36","count":"10406"}
,{"year":"2019","month":"10","pickup_community_area":"37","count":"7075"}
,{"year":"2019","month":"10","pickup_community_area":"38","count":"46994"}
,{"year":"2019","month":"10","pickup_community_area":"39","count":"38039"}
,{"year":"2019","month":"10","pickup_community_area":"40","count":"22439"}
,{"year":"2019","month":"10","pickup_community_area":"41","count":"141370"}
,{"year":"2019","month":"10","pickup_community_area":"42","count":"45565"}
,{"year":"2019","month":"10","pickup_community_area":"43","count":"63575"}
,{"year":"2019","month":"10","pickup_community_area":"44","count":"50001"}
,{"year":"2019","month":"10","pickup_community_area":"45","count":"9827"}
,{"year":"2019","month":"10","pickup_community_area":"46","count":"20656"}
,{"year":"2019","month":"10","pickup_community_area":"47","count":"3342"}
,{"year":"2019","month":"10","pickup_community_area":"48","count":"10604"}
,{"year":"2019","month":"10","pickup_community_area":"49","count":"40730"}
,{"year":"2019","month":"10","pickup_community_area":"50","count":"9830"}
,{"year":"2019","month":"10","pickup_community_area":"51","count":"11541"}
,{"year":"2019","month":"10","pickup_community_area":"52","count":"4253"}
,{"year":"2019","month":"10","pickup_community_area":"53","count":"18222"}
,{"year":"2019","month":"10","pickup_community_area":"54","count":"5190"}
,{"year":"2019","month":"10","pickup_community_area":"55","count":"4228"}
,{"year":"2019","month":"10","pickup_community_area":"56","count":"132326"}
,{"year":"2019","month":"10","pickup_community_area":"57","count":"17382"}
,{"year":"2019","month":"10","pickup_community_area":"58","count":"36140"}
,{"year":"2019","month":"10","pickup_community_area":"59","count":"20605"}
,{"year":"2019","month":"10","pickup_community_area":"60","count":"48689"}
,{"year":"2019","month":"10","pickup_community_area":"61","count":"39387"}
,{"year":"2019","month":"10","pickup_community_area":"62","count":"12894"}
,{"year":"2019","month":"10","pickup_community_area":"63","count":"25020"}
,{"year":"2019","month":"10","pickup_community_area":"64","count":"13209"}
,{"year":"2019","month":"10","pickup_community_area":"65","count":"23244"}
,{"year":"2019","month":"10","pickup_community_area":"66","count":"39760"}
,{"year":"2019","month":"10","pickup_community_area":"67","count":"27969"}
,{"year":"2019","month":"10","pickup_community_area":"68","count":"35064"}
,{"year":"2019","month":"10","pickup_community_area":"69","count":"45374"}
,{"year":"2019","month":"10","pickup_community_area":"70","count":"24128"}
,{"year":"2019","month":"10","pickup_community_area":"71","count":"44391"}
,{"year":"2019","month":"10","pickup_community_area":"72","count":"11812"}
,{"year":"2019","month":"10","pickup_community_area":"73","count":"21722"}
,{"year":"2019","month":"10","pickup_community_area":"74","count":"7028"}
,{"year":"2019","month":"10","pickup_community_area":"75","count":"14535"}
,{"year":"2019","month":"10","pickup_community_area":"76","count":"408473"}
,{"year":"2019","month":"10","pickup_community_area":"77","count":"125953"}
,{"year":"2019","month":"10","count":"640372"}
,{"year":"2019","month":"11","pickup_community_area":"1","count":"102104"}
,{"year":"2019","month":"11","pickup_community_area":"2","count":"72442"}
,{"year":"2019","month":"11","pickup_community_area":"3","count":"195754"}
,{"year":"2019","month":"11","pickup_community_area":"4","count":"96504"}
,{"year":"2019","month":"11","pickup_community_area":"5","count":"111323"}
,{"year":"2019","month":"11","pickup_community_area":"6","count":"595859"}
,{"year":"2019","month":"11","pickup_community_area":"7","count":"498191"}
,{"year":"2019","month":"11","pickup_community_area":"8","count":"1521383"}
,{"year":"2019","month":"11","pickup_community_area":"9","count":"9614"}
,{"year":"2019","month":"11","pickup_community_area":"10","count":"28243"}
,{"year":"2019","month":"11","pickup_community_area":"11","count":"23892"}
,{"year":"2019","month":"11","pickup_community_area":"12","count":"12382"}
,{"year":"2019","month":"11","pickup_community_area":"13","count":"21454"}
,{"year":"2019","month":"11","pickup_community_area":"14","count":"58659"}
,{"year":"2019","month":"11","pickup_community_area":"15","count":"58955"}
,{"year":"2019","month":"11","pickup_community_area":"16","count":"88489"}
,{"year":"2019","month":"11","pickup_community_area":"17","count":"25096"}
,{"year":"2019","month":"11","pickup_community_area":"18","count":"9312"}
,{"year":"2019","month":"11","pickup_community_area":"19","count":"66096"}
,{"year":"2019","month":"11","pickup_community_area":"20","count":"24233"}
,{"year":"2019","month":"11","pickup_community_area":"21","count":"99746"}
,{"year":"2019","month":"11","pickup_community_area":"22","count":"339601"}
,{"year":"2019","month":"11","pickup_community_area":"23","count":"72485"}
,{"year":"2019","month":"11","pickup_community_area":"24","count":"572126"}
,{"year":"2019","month":"11","pickup_community_area":"25","count":"94863"}
,{"year":"2019","month":"11","pickup_community_area":"26","count":"21777"}
,{"year":"2019","month":"11","pickup_community_area":"27","count":"34275"}
,{"year":"2019","month":"11","pickup_community_area":"28","count":"820808"}
,{"year":"2019","month":"11","pickup_community_area":"29","count":"54888"}
,{"year":"2019","month":"11","pickup_community_area":"30","count":"56134"}
,{"year":"2019","month":"11","pickup_community_area":"31","count":"113210"}
,{"year":"2019","month":"11","pickup_community_area":"32","count":"813040"}
,{"year":"2019","month":"11","pickup_community_area":"33","count":"180993"}
,{"year":"2019","month":"11","pickup_community_area":"34","count":"42969"}
,{"year":"2019","month":"11","pickup_community_area":"35","count":"54304"}
,{"year":"2019","month":"11","pickup_community_area":"36","count":"9883"}
,{"year":"2019","month":"11","pickup_community_area":"37","count":"7297"}
,{"year":"2019","month":"11","pickup_community_area":"38","count":"48041"}
,{"year":"2019","month":"11","pickup_community_area":"39","count":"38341"}
,{"year":"2019","month":"11","pickup_community_area":"40","count":"23065"}
,{"year":"2019","month":"11","pickup_community_area":"41","count":"137030"}
,{"year":"2019","month":"11","pickup_community_area":"42","count":"47769"}
,{"year":"2019","month":"11","pickup_community_area":"43","count":"67265"}
,{"year":"2019","month":"11","pickup_community_area":"44","count":"53787"}
,{"year":"2019","month":"11","pickup_community_area":"45","count":"10425"}
,{"year":"2019","month":"11","pickup_community_area":"46","count":"22517"}
,{"year":"2019","month":"11","pickup_community_area":"47","count":"3373"}
,{"year":"2019","month":"11","pickup_community_area":"48","count":"11205"}
,{"year":"2019","month":"11","pickup_community_area":"49","count":"42601"}
,{"year":"2019","month":"11","pickup_community_area":"50","count":"9929"}
,{"year":"2019","month":"11","pickup_community_area":"51","count":"11667"}
,{"year":"2019","month":"11","pickup_community_area":"52","count":"4239"}
,{"year":"2019","month":"11","pickup_community_area":"53","count":"19186"}
,{"year":"2019","month":"11","pickup_community_area":"54","count":"5806"}
,{"year":"2019","month":"11","pickup_community_area":"55","count":"3938"}
,{"year":"2019","month":"11","pickup_community_area":"56","count":"115128"}
,{"year":"2019","month":"11","pickup_community_area":"57","count":"16953"}
,{"year":"2019","month":"11","pickup_community_area":"58","count":"36639"}
,{"year":"2019","month":"11","pickup_community_area":"59","count":"20482"}
,{"year":"2019","month":"11","pickup_community_area":"60","count":"48082"}
,{"year":"2019","month":"11","pickup_community_area":"61","count":"40889"}
,{"year":"2019","month":"11","pickup_community_area":"62","count":"13430"}
,{"year":"2019","month":"11","pickup_community_area":"63","count":"25146"}
,{"year":"2019","month":"11","pickup_community_area":"64","count":"12965"}
,{"year":"2019","month":"11","pickup_community_area":"65","count":"22849"}
,{"year":"2019","month":"11","pickup_community_area":"66","count":"41830"}
,{"year":"2019","month":"11","pickup_community_area":"67","count":"30131"}
,{"year":"2019","month":"11","pickup_community_area":"68","count":"36817"}
,{"year":"2019","month":"11","pickup_community_area":"69","count":"47915"}
,{"year":"2019","month":"11","pickup_community_area":"70","count":"24691"}
,{"year":"2019","month":"11","pickup_community_area":"71","count":"47212"}
,{"year":"2019","month":"11","pickup_community_area":"72","count":"13480"}
,{"year":"2019","month":"11","pickup_community_area":"73","count":"22652"}
,{"year":"2019","month":"11","pickup_community_area":"74","count":"8148"}
,{"year":"2019","month":"11","pickup_community_area":"75","count":"16338"}
,{"year":"2019","month":"11","pickup_community_area":"76","count":"342714"}
,{"year":"2019","month":"11","pickup_community_area":"77","count":"130001"}
,{"year":"2019","month":"11","count":"622387"}
,{"year":"2019","month":"12","pickup_community_area":"1","count":"99551"}
,{"year":"2019","month":"12","pickup_community_area":"2","count":"74064"}
,{"year":"2019","month":"12","pickup_community_area":"3","count":"197154"}
,{"year":"2019","month":"12","pickup_community_area":"4","count":"95364"}
,{"year":"2019","month":"12","pickup_community_area":"5","count":"114217"}
,{"year":"2019","month":"12","pickup_community_area":"6","count":"601957"}
,{"year":"2019","month":"12","pickup_community_area":"7","count":"499375"}
,{"year":"2019","month":"12","pickup_community_area":"8","count":"1531819"}
,{"year":"2019","month":"12","pickup_community_area":"9","count":"10391"}
,{"year":"2019","month":"12","pickup_community_area":"10","count":"29026"}
,{"year":"2019","month":"12","pickup_community_area":"11","count":"25119"}
,{"year":"2019","month":"12","pickup_community_area":"12","count":"13076"}
,{"year":"2019","month":"12","pickup_community_area":"13","count":"19864"}
,{"year":"2019","month":"12","pickup_community_area":"14","count":"57453"}
,{"year":"2019","month":"12","pickup_community_area":"15","count":"60015"}
,{"year":"2019","month":"12","pickup_community_area":"16","count":"90919"}
,{"year":"2019","month":"12","pickup_community_area":"17","count":"25415"}
,{"year":"2019","month":"12","pickup_community_area":"18","count":"9591"}
,{"year":"2019","month":"12","pickup_community_area":"19","count":"66766"}
,{"year":"2019","month":"12","pickup_community_area":"20","count":"23854"}
,{"year":"2019","month":"12","pickup_community_area":"21","count":"99429"}
,{"year":"2019","month":"12","pickup_community_area":"22","count":"335139"}
,{"year":"2019","month":"12","pickup_community_area":"23","count":"74669"}
,{"year":"2019","month":"12","pickup_community_area":"24","count":"559319"}
,{"year":"2019","month":"12","pickup_community_area":"25","count":"98495"}
,{"year":"2019","month":"12","pickup_community_area":"26","count":"22402"}
,{"year":"2019","month":"12","pickup_community_area":"27","count":"35615"}
,{"year":"2019","month":"12","pickup_community_area":"28","count":"798477"}
,{"year":"2019","month":"12","pickup_community_area":"29","count":"55804"}
,{"year":"2019","month":"12","pickup_community_area":"30","count":"56662"}
,{"year":"2019","month":"12","pickup_community_area":"31","count":"108504"}
,{"year":"2019","month":"12","pickup_community_area":"32","count":"802811"}
,{"year":"2019","month":"12","pickup_community_area":"33","count":"181678"}
,{"year":"2019","month":"12","pickup_community_area":"34","count":"39346"}
,{"year":"2019","month":"12","pickup_community_area":"35","count":"51557"}
,{"year":"2019","month":"12","pickup_community_area":"36","count":"10356"}
,{"year":"2019","month":"12","pickup_community_area":"37","count":"7369"}
,{"year":"2019","month":"12","pickup_community_area":"38","count":"49367"}
,{"year":"2019","month":"12","pickup_community_area":"39","count":"37786"}
,{"year":"2019","month":"12","pickup_community_area":"40","count":"23407"}
,{"year":"2019","month":"12","pickup_community_area":"41","count":"108811"}
,{"year":"2019","month":"12","pickup_community_area":"42","count":"44871"}
,{"year":"2019","month":"12","pickup_community_area":"43","count":"69260"}
,{"year":"2019","month":"12","pickup_community_area":"44","count":"55689"}
,{"year":"2019","month":"12","pickup_community_area":"45","count":"10350"}
,{"year":"2019","month":"12","pickup_community_area":"46","count":"23258"}
,{"year":"2019","month":"12","pickup_community_area":"47","count":"3498"}
,{"year":"2019","month":"12","pickup_community_area":"48","count":"11907"}
,{"year":"2019","month":"12","pickup_community_area":"49","count":"44535"}
,{"year":"2019","month":"12","pickup_community_area":"50","count":"9911"}
,{"year":"2019","month":"12","pickup_community_area":"51","count":"12508"}
,{"year":"2019","month":"12","pickup_community_area":"52","count":"4335"}
,{"year":"2019","month":"12","pickup_community_area":"53","count":"19947"}
,{"year":"2019","month":"12","pickup_community_area":"54","count":"6094"}
,{"year":"2019","month":"12","pickup_community_area":"55","count":"3876"}
,{"year":"2019","month":"12","pickup_community_area":"56","count":"115217"}
,{"year":"2019","month":"12","pickup_community_area":"57","count":"16687"}
,{"year":"2019","month":"12","pickup_community_area":"58","count":"37302"}
,{"year":"2019","month":"12","pickup_community_area":"59","count":"20757"}
,{"year":"2019","month":"12","pickup_community_area":"60","count":"48582"}
,{"year":"2019","month":"12","pickup_community_area":"61","count":"40975"}
,{"year":"2019","month":"12","pickup_community_area":"62","count":"13016"}
,{"year":"2019","month":"12","pickup_community_area":"63","count":"24903"}
,{"year":"2019","month":"12","pickup_community_area":"64","count":"13378"}
,{"year":"2019","month":"12","pickup_community_area":"65","count":"22907"}
,{"year":"2019","month":"12","pickup_community_area":"66","count":"43001"}
,{"year":"2019","month":"12","pickup_community_area":"67","count":"31983"}
,{"year":"2019","month":"12","pickup_community_area":"68","count":"37785"}
,{"year":"2019","month":"12","pickup_community_area":"69","count":"51235"}
,{"year":"2019","month":"12","pickup_community_area":"70","count":"25564"}
,{"year":"2019","month":"12","pickup_community_area":"71","count":"49817"}
,{"year":"2019","month":"12","pickup_community_area":"72","count":"14966"}
,{"year":"2019","month":"12","pickup_community_area":"73","count":"24080"}
,{"year":"2019","month":"12","pickup_community_area":"74","count":"8596"}
,{"year":"2019","month":"12","pickup_community_area":"75","count":"17372"}
,{"year":"2019","month":"12","pickup_community_area":"76","count":"316730"}
,{"year":"2019","month":"12","pickup_community_area":"77","count":"130134"}
,{"year":"2019","month":"12","count":"614462"}]
